sci_cache/__init__.py
sci_cache/method_cache/__init__.py
sci_cache/method_cache/handlers.py
sci_cache/method_cache/init.py
sci_cache/method_cache/inner_cache.py
sci_cache/method_cache/method_cache.py
sci_cache-0.1.4.dist-info/LICENSE
sci_cache-0.1.4.dist-info/METADATA
sci_cache-0.1.4.dist-info/WHEEL
sci_cache-0.1.4.dist-info/RECORD
