Metadata-Version: 2.1
Name: sci-cache
Version: 0.1.4
Summary: A Python library for caching scientific data on disk, streamlining research workflows by storing intermediate results.
Home-page: https://github.com/panhaoyu/sci-cache
License: MIT
Keywords: cache,scientific,data,performance,optimization
Author: panhaoyu
Author-email: panhaoyu.china@outlook.com
Requires-Python: >=3.10,<4.0
Classifier: Development Status :: 4 - Beta
Classifier: Intended Audience :: Developers
Classifier: Intended Audience :: Science/Research
Classifier: License :: OSI Approved :: MIT License
Classifier: Programming Language :: Python :: 3
Classifier: Programming Language :: Python :: 3.10
Classifier: Programming Language :: Python :: 3.11
Classifier: Programming Language :: Python :: 3.12
Classifier: Topic :: Scientific/Engineering :: Information Analysis
Classifier: Topic :: Software Development :: Libraries :: Python Modules
Requires-Dist: pypinyin (>=0.53.0,<0.54.0)
Project-URL: Documentation, https://github.com/panhaoyu/sci-cache
Project-URL: Repository, https://github.com/panhaoyu/sci-cache
